ssppy/__init__.py
ssppy/energy_functions.py
ssppy/power_functions.py
ssppy/reader_functions.py
ssppy/shadow_functions.py
ssppy/ssppy.py
ssppy/visibility_functions.py
ssppy-0.1.0.dist-info/LICENSE
ssppy-0.1.0.dist-info/METADATA
ssppy-0.1.0.dist-info/WHEEL
ssppy-0.1.0.dist-info/RECORD
