Metadata-Version: 2.1
Name: ssppy
Version: 0.1.0
Summary: Compute energy potential of space solar power 
License: MIT
Author: Jack Mcnish
Requires-Python: >=3.9,<3.12
Classifier: License :: OSI Approved :: MIT License
Classifier: Programming Language :: Python :: 3
Classifier: Programming Language :: Python :: 3.9
Classifier: Programming Language :: Python :: 3.10
Classifier: Programming Language :: Python :: 3.11
Requires-Dist: matplotlib (>=3.7.1,<4.0.0)
Requires-Dist: myst-nb (>=0.17.1,<0.18.0)
Requires-Dist: numpy (>=1.24.2,<2.0.0)
Requires-Dist: pandas (>=2.0.0,<3.0.0)
Requires-Dist: scipy (>=1.10.1,<2.0.0)
